djangocms_local_navigation/__init__.py
djangocms_local_navigation/cms_plugin_processors.py
djangocms_local_navigation/cms_plugins.py
djangocms_local_navigation/conf.py
djangocms_local_navigation/utils.py
djangocms_local_navigation/templates/djangocms_local_navigation/menu.html
djangocms_local_navigation-1.4.1.dist-info/DESCRIPTION.rst
djangocms_local_navigation-1.4.1.dist-info/METADATA
djangocms_local_navigation-1.4.1.dist-info/RECORD
djangocms_local_navigation-1.4.1.dist-info/WHEEL
djangocms_local_navigation-1.4.1.dist-info/metadata.json
djangocms_local_navigation-1.4.1.dist-info/top_level.txt
