Metadata-Version: 2.0
Name: djangocms-local-navigation
Version: 1.4.1
Summary: Display menus based on the HTML structure of the pages
Home-page: https://github.com/liip/djangocms-local-navigation
Author: Sylvain Fankhauser
Author-email: sylvain.fankhauser@liip.ch
License: BSD
Platform: UNKNOWN
Classifier: Development Status :: 5 - Production/Stable
Classifier: Framework :: Django
Classifier: Programming Language :: Python :: 2
Classifier: Programming Language :: Python :: 2.7
Classifier: Programming Language :: Python :: 3
Classifier: Programming Language :: Python :: 3.4
Classifier: Programming Language :: Python :: 3.5
Requires-Dist: beautifulsoup4
Requires-Dist: django-cms (>=3.0)
